LICENSE
README.md
setup.py
acleto/__init__.py
acleto.egg-info/PKG-INFO
acleto.egg-info/SOURCES.txt
acleto.egg-info/dependency_links.txt
acleto.egg-info/requires.txt
acleto.egg-info/top_level.txt
acleto/al4nlp/__init__.py
acleto/al4nlp/active_learner.py
acleto/al4nlp/active_selector.py
acleto/al4nlp/constructors/__init__.py
acleto/al4nlp/constructors/construct_active_learner.py
acleto/al4nlp/constructors/construct_wrapper.py
acleto/al4nlp/model_wrappers/__init__.py
acleto/al4nlp/model_wrappers/flair/__init__.py
acleto/al4nlp/model_wrappers/flair/flair_trainer.py
acleto/al4nlp/model_wrappers/flair/wrapper_flair.py
acleto/al4nlp/model_wrappers/pytorch/__init__.py
acleto/al4nlp/model_wrappers/pytorch/wrapper_cls_pytorch.py
acleto/al4nlp/model_wrappers/pytorch/wrapper_encoder_pytorch.py
acleto/al4nlp/model_wrappers/pytorch/wrapper_ner_pytorch.py
acleto/al4nlp/model_wrappers/transformers/__init__.py
acleto/al4nlp/model_wrappers/transformers/trainer_for_pseudo_labeled.py
acleto/al4nlp/model_wrappers/transformers/transformers_base_wrapper.py
acleto/al4nlp/model_wrappers/transformers/wrapper_ats.py
acleto/al4nlp/model_wrappers/transformers/wrapper_cls.py
acleto/al4nlp/model_wrappers/transformers/wrapper_encoder.py
acleto/al4nlp/model_wrappers/transformers/wrapper_ner.py
acleto/al4nlp/model_wrappers/transformers/wrapper_nmt.py
acleto/al4nlp/model_wrappers/transformers/wrapper_seq2seq.py
acleto/al4nlp/models/__init__.py
acleto/al4nlp/models/bilstm_crf.py
acleto/al4nlp/models/fnet.py
acleto/al4nlp/models/ner_bilstm.py
acleto/al4nlp/models/text_classification_cnn.py
acleto/al4nlp/models/spectral_normalization/__init__.py
acleto/al4nlp/models/spectral_normalization/spectral_norm_conv_inplace.py
acleto/al4nlp/models/spectral_normalization/spectral_norm_fc.py
acleto/al4nlp/pool_subsampling_strategies/__init__.py
acleto/al4nlp/pool_subsampling_strategies/naive_subsampling.py
acleto/al4nlp/pool_subsampling_strategies/random_subsampling.py
acleto/al4nlp/pool_subsampling_strategies/ups_subsampling.py
acleto/al4nlp/query_strategies/__init__.py
acleto/al4nlp/query_strategies/actune.py
acleto/al4nlp/query_strategies/akim.py
