Metadata-Version: 2.1
Name: acleto
Version: 0.0.7
Summary: A Library for active learning. Supports text classification and sequence tagging tasks.
Home-page: UNKNOWN
Author: Tsvigun A., Sanochkin L., Kuzmin G., Larionov D., and Dr Shelmanov A.
License: MIT
Keywords: NLP active AL deep learning transformer pytorch PLASM UPS
Platform: UNKNOWN
Provides-Extra: small-text
Provides-Extra: modAL
License-File: LICENSE
